{
    "profiles": [
        {
            "example_profile": [
                {
                    "1": {"mo": "to", "x": "r", "y": "none"},
                    "2": {"mo": "ta", "x": "r","y": "none"},
                    "3": {"mo": "lcl", "x": "none","y": "none"},
                    "4": {"mo": "rcl", "x": "none", "y": "none"},
                    "5": {"mo": "sc", "x": "10", "y": "10", "pn": "+-"},
                    "6": {"mo": "mv", "x": "10", "y": "10", "pn": "++"},
                    "7": {"mo": "mu", "x": "10", "y": "10", "pn": "--"}
                }
            ]
        }
    ]
}